gistsight/__init__.py
gistsight/conf_sample.py
gistsight/config.py
gistsight/monitoring.py
gistsight/publish.py
gistsight-1.1.0.dist-info/COPYING
gistsight-1.1.0.dist-info/METADATA
gistsight-1.1.0.dist-info/WHEEL
gistsight-1.1.0.dist-info/entry_points.txt
gistsight-1.1.0.dist-info/RECORD
