Metadata-Version: 2.3
Name: GistSight
Version: 1.1.0
Summary: A client for gathering vulnerability-related information from GitHub Gists.
License: GPL-3.0-or-later
Keywords: Vulnerability-Lookup,Vulnerability,CVE,GitHub,Gist
Author: Cédric Bonhomme
Author-email: cedric.bonhomme@circl.lu
Requires-Python: >=3.10,<4.0
Classifier: Development Status :: 5 - Production/Stable
Classifier: Environment :: Console
Classifier: Intended Audience :: Developers
Classifier: Intended Audience :: Science/Research
Classifier: License :: OSI Approved :: GNU General Public License v3 or later (GPLv3+)
Classifier: Operating System :: POSIX :: Linux
Classifier: Programming Language :: Python :: 3
Classifier: Programming Language :: Python :: 3.10
Classifier: Programming Language :: Python :: 3.11
Classifier: Programming Language :: Python :: 3.12
Classifier: Programming Language :: Python :: 3.13
Classifier: Topic :: Security
Requires-Dist: pyvulnerabilitylookup (>=2.2.0)
Requires-Dist: requests (>=2.32.3)
Requires-Dist: valkey (>=6.1.0,<7.0.0)
Project-URL: Changelog, https://github.com/vulnerability-lookup/GistSight/blob/main/CHANGELOG.md
Project-URL: Homepage, https://github.com/vulnerability-lookup/GistSight
Project-URL: Repository, https://github.com/vulnerability-lookup/GistSight
